Math/__init__.py
Math/formulas.py
vpython_zth_math-0.0.1.dist-info/METADATA
vpython_zth_math-0.0.1.dist-info/WHEEL
vpython_zth_math-0.0.1.dist-info/top_level.txt
vpython_zth_math-0.0.1.dist-info/RECORD
