Metadata-Version: 2.1
Name: vpython-zth-math
Version: 0.0.1
Summary: Learn to publish my first package
Author: Maslia Qomar
Author-email: <lhiyaq@gmail.com>
License: UNKNOWN
Keywords: python,math,learn
Platform: UNKNOWN
Classifier: Development Status :: 1 - Planning
Classifier: Intended Audience :: Developers
Classifier: Programming Language :: Python :: 3
Classifier: Operating System :: Unix
Classifier: Operating System :: MacOS :: MacOS X
Classifier: Operating System :: Microsoft :: Windows
